odoo/addons/helpdesk_ticket_api/README.rst
odoo/addons/helpdesk_ticket_api/__init__.py
odoo/addons/helpdesk_ticket_api/__manifest__.py
odoo/addons/helpdesk_ticket_api/demo/helpdesk_ticket_category.xml
odoo/addons/helpdesk_ticket_api/demo/helpdesk_ticket_channel.xml
odoo/addons/helpdesk_ticket_api/demo/helpdesk_ticket_stage.xml
odoo/addons/helpdesk_ticket_api/demo/helpdesk_ticket_tag.xml
odoo/addons/helpdesk_ticket_api/demo/helpdesk_ticket_team.xml
odoo/addons/helpdesk_ticket_api/i18n/ca_ES.po
odoo/addons/helpdesk_ticket_api/i18n/es.po
odoo/addons/helpdesk_ticket_api/models/__init__.py
odoo/addons/helpdesk_ticket_api/models/helpdesk_ticket_category.py
odoo/addons/helpdesk_ticket_api/models/helpdesk_ticket_channel.py
odoo/addons/helpdesk_ticket_api/models/helpdesk_ticket_stage.py
odoo/addons/helpdesk_ticket_api/models/helpdesk_ticket_tag.py
odoo/addons/helpdesk_ticket_api/models/helpdesk_ticket_team.py
odoo/addons/helpdesk_ticket_api/services/__init__.py
odoo/addons/helpdesk_ticket_api/services/helpdesk_ticket_service.py
odoo/addons/helpdesk_ticket_api/services/schemas.py
odoo/addons/helpdesk_ticket_api/static/description/icon.png
odoo/addons/helpdesk_ticket_api/tests/__init__.py
odoo/addons/helpdesk_ticket_api/tests/test_ticket_service.py
odoo/addons/helpdesk_ticket_api/views/helpdesk_ticket_category.xml
odoo/addons/helpdesk_ticket_api/views/helpdesk_ticket_channel.xml
odoo/addons/helpdesk_ticket_api/views/helpdesk_ticket_stage.xml
odoo/addons/helpdesk_ticket_api/views/helpdesk_ticket_tag.xml
odoo/addons/helpdesk_ticket_api/views/helpdesk_ticket_team.xml
odoo12_addon_helpdesk_ticket_api-12.0.0.1.0.99.dev2.dist-info/METADATA
odoo12_addon_helpdesk_ticket_api-12.0.0.1.0.99.dev2.dist-info/WHEEL
odoo12_addon_helpdesk_ticket_api-12.0.0.1.0.99.dev2.dist-info/top_level.txt
odoo12_addon_helpdesk_ticket_api-12.0.0.1.0.99.dev2.dist-info/RECORD
